nfa/__init__.py
nfa/nfa.py
nfa-3.1.0.dist-info/LICENSE
nfa-3.1.0.dist-info/METADATA
nfa-3.1.0.dist-info/WHEEL
nfa-3.1.0.dist-info/top_level.txt
nfa-3.1.0.dist-info/RECORD
